{
  "parent": "minecraft:recipes/root",
  "criteria": {
    "has_potato_crate": {
      "conditions": {
        "items": [
          {
            "items": "borukva-food:potato_crate"
          }
        ]
      },
      "trigger": "minecraft:inventory_changed"
    },
    "has_the_recipe": {
      "conditions": {
        "recipe": "borukva-food:potato_crate_to_potato"
      },
      "trigger": "minecraft:recipe_unlocked"
    }
  },
  "requirements": [
    [
      "has_the_recipe",
      "has_potato_crate"
    ]
  ],
  "rewards": {
    "recipes": [
      "borukva-food:potato_crate_to_potato"
    ]
  }
}